MANIFEST.in
README
__init__.py
__pkginfo__.py
entities.py
hooks.py
schema.py
setup.py
views.py
./__init__.py
./__pkginfo__.py
./entities.py
./hooks.py
./schema.py
./views.py
./test/pytestconf.py
./test/realdb_test_testcard.py
./test/unittest_hooks.py
cubicweb_testcard.egg-info/PKG-INFO
cubicweb_testcard.egg-info/SOURCES.txt
cubicweb_testcard.egg-info/dependency_links.txt
cubicweb_testcard.egg-info/not-zip-safe
cubicweb_testcard.egg-info/requires.txt
cubicweb_testcard.egg-info/top_level.txt
i18n/en.po
i18n/fr.po
migration/postcreate.py