Metadata-Version: 1.0
Name: cubicweb-testcard
Version: 0.4.0
Summary: test card extension for CubicWeb application based on the tracker cube
Home-page: http://www.cubicweb.org/project/cubicweb-testcard
Author: LOGILAB S.A. (Paris, FRANCE)
Author-email: contact@logilab.fr
License: LGPL
Platform: UNKNOWN
